{
    "modsRequired": ["pamhc2foodcore"],
    "content": [
        {
            "type": "item",
            "content": "pamhcfoodcore:stewitem",
            "amountRange": {
                "min": 1,
                "max": 15
            },
            "unitWorth": 500
        },
        {
            "type": "item",
            "content": "pamhcfoodcore:potatosoupitem",
            "amountRange": {
                "min": 1,
                "max": 15
            },
            "unitWorth": 500
        },
        {
            "type": "item",
            "content": "pamhcfoodcore:potatosoupitem",
            "amountRange": {
                "min": 1,
                "max": 5
            },
            "unitWorth": 500
        }
        {"type": "item", "content":"pamhc2foodcore:mayonaiseitem", "amountRange": {"min": 1, "max": 5}, "unitWorth": 200, "weight": 1000},
        {"type": "item", "content":"pamhc2foodcore:butteritem", "amountRange": {"min": 1, "max": 5}, "unitWorth": 200, "weight": 1000},
        {"type": "item", "content":"pamhc2foodcore:cheeseitem", "amountRange": {"min": 1, "max": 5}, "unitWorth": 200, "weight": 1000},
        {"type": "item", "content":"pamhc2foodcore:creamitem", "amountRange": {"min": 1, "max": 5}, "unitWorth": 200, "weight": 1000},
        {"type": "item", "content":"pamhc2foodcore:batteritem", "amountRange": {"min": 1, "max": 5}, "unitWorth": 200, "weight": 1000},
        {"type": "item", "content":"pamhc2foodcore:flouritem", "amountRange": {"min": 1, "max": 5}, "unitWorth": 200, "weight": 1000},
        {"type": "item", "content":"pamhc2foodcore:doughitem", "amountRange": {"min": 1, "max": 5}, "unitWorth": 200, "weight": 1000},
        {"type": "item", "content":"pamhc2foodcore:vinegaritem", "amountRange": {"min": 1, "max": 5}, "unitWorth": 200, "weight": 1000}
    ]
}
